proc/proc.v
/*

**********Module Proc.v*************
Functions executed :
  1 - AND
  2 - ADD
  3 - FETCH

  The third operation takes in the argument last 8 bit operand in the
  instruction input to check the memory location and return the value
  found and also copies the same into the destination register as well.
*/
module proc(
  input clk,
  input [31:0] instr,
  output [8:0] res
  );
  
  //Storage array to store the computed results.
  //Each of the elements in this array are 9 bits in size in order to accomodate
  // the 8 bit sum and 1 bit carry formed by adding two 8 bit numbers
  reg [8:0] storage [7:0];

  //Control signals to control the muxes in the execute stage
  reg instr_and, instr_add, instr_fetch;

  //Data to be passed onto the execute stage along with the control signals
  reg [23:0] data_exec;
  
  //instr_decode
  //Decode the first 8 bits of the decode stage to generate the control signals
  always@(posedge clk)
  begin
    //Initialize the values to zero 
    instr_add <= 0;
    instr_and <= 0;
    instr_fetch <= 0;
    //Update only the signal corresponding to the instruction
    if(instr[31:24] == 0)
      instr_and <= 1;
    else if(instr[31:24] == 1)
      instr_add <= 1;
    else if(instr[31:24] == 2)
      instr_fetch <= 1;
    //Pass the memory location and operands from the instruction to the execute stage
    data_exec <= instr[23:0];
  end

  //Data to be written to the storage location in write_back stage
  reg [8:0] data_write;
  reg temp_carry;
  reg [7:0] temp_sum;
  //Location registers from the instr to be passed to the write_back stage
  reg [7:0] location_write;
  
  //instr_execute
  //Executes the operation based on the control signals
  always@(posedge clk)
  begin
    if(instr_add == 1)
    begin
      data_write <= data_exec[7:0] + data_exec[15:8];
    end
    else if(instr_and == 1)
    begin
      data_write <= data_exec[7:0] & data_exec [15:8];
    end
    //This operation instr_fetch fetches the data stored in the storage location requested
    else if(instr_fetch == 1)
    begin
      data_write <= storage[data_exec[7:0]];
    end

    //Pass the location to write back to the next stage
    location_write <= data_exec [23:16];
  end


  //write_back stage
  //This stage takes the result and storage location from the previous stage
  // stores them in the location requested. Also, it assigns the result to
  // res output of the module.
  always@(posedge clk)
  begin
    storage[location_write] <= data_write;
  end
  assign res = data_write;

endmodule

proc/tb_proc.v
module tb_proc();
  //Variable declaration
  reg clk;
  reg [31:0] instr;

  //****Please note that the result is of size 9 bits in order to accomodate the carry bit*****
  wire [8:0] res;
  //proc module instantiation
  proc p1(clk, instr, res);

  reg [7:0] temp [0:3]; //An array of 4 elements which together constitute the 32 bit instr

  initial begin
    clk = 0;
    //Dump the values of all the variables into the dumpfile
    $dumpfile("a.vcd");
    $dumpvars;
    /*For the following instructions,
    	temp[3] = opcode;
    	temp[2] = data_destination;
    	temp[1] = operand_1;
    	temp[0] = operand_2;
    */ 
    //Instr_1
    //Instr to "and" the operands
    temp[3] = 0; temp[2] = 3;temp[1] = 57;temp[0] = 100;
    @(posedge clk) instr <= {temp[3], temp[2], temp[1], temp[0]};
    //Instr_2
    //Instr to "add" the operands
    temp[3] = 1; temp[2] = 4;temp[1] = 255;temp[0] = 255;
    @(posedge clk) instr <= {temp[3], temp[2], temp[1], temp[0]};
    //Instr_3
    //Instr to display the data in the memory location temp[0]
    temp[3] = 2; temp[2] = 5;temp[1] = 57;temp[0] = 3;
    @(posedge clk) instr <= {temp[3], temp[2], temp[1], temp[0]};
    //Instr_4
    //Instr to display the data in the memory location temp[0]
    temp[3] = 2; temp[2] = 6;temp[1] = 57;temp[0] = 4;
    @(posedge clk) instr <= {temp[3], temp[2], temp[1], temp[0]};
    //Finish the execution after 100 clock units
    #100 $finish;
  end

  always
  begin
  	//Alternate the clock after every 5 clock units, effective clock delay is 10 units
    #5 clk = ~clk;
  end

endmodule

proc/a.vcd
$date
	Fri May  3 01:41:30 2019
$end
$version
	Icarus Verilog
$end
$timescale
	1s
$end
$scope module tb_proc $end
$var wire 9 ! res [8:0] $end
$var reg 1 " clk $end
$var reg 32 # instr [31:0] $end
$scope module p1 $end
$var wire 1 " clk $end
$var wire 32 $ instr [31:0] $end
$var wire 9 % res [8:0] $end
$var reg 24 & data_exec [23:0] $end
$var reg 9 ' data_write [8:0] $end
$var reg 1 ( instr_add $end
$var reg 1 ) instr_and $end
$var reg 1 * instr_fetch $end
$var reg 8 + location_write [7:0] $end
$upscope $end
$upscope $end
$enddefinitions $end
#0
$dumpvars
bx +
x*
x)
x(
bx '
bx &
bx %
bx $
bx #
0"
bx !
$end
#5
0*
0)
0(
b110011100101100100 #
b110011100101100100 $
1"
#10
0"
#15
b1000001001111111111111111 #
b1000001001111111111111111 $
b110011100101100100 &
1)
1"
#20
0"
#25
b1001111111111111111 &
1(
0)
b11 +
b100000 !
b100000 %
b100000 '
b10000001010011100100000011 #
b10000001010011100100000011 $
1"
#30
0"
#35
b10000001100011100100000100 #
b10000001100011100100000100 $
b100 +
b111111110 !
b111111110 %
b111111110 '
b1010011100100000011 &
1*
0(
1"
#40
0"
#45
b1100011100100000100 &
1*
b101 +
b100000 !
b100000 %
b100000 '
1"
#50
0"
#55
b110 +
b111111110 !
b111111110 %
b111111110 '
1*
1"
#60
0"
#65
1*
1"
#70
0"
#75
1*
1"
#80
0"
#85
1*
1"
#90
0"
#95
1*
1"
#100
0"
#105
1*
1"
#110
0"
#115
1*
1"
#120
0"
#125
1*
1"
#130
0"
#135
1*
1"
