lab_7/wide_adder_pipe.v
module fa(output wire s, cout, input wire a, b, cin);
    assign {cout, s} = cin + a + b;
endmodule

module wide_adder #(parameter [3:0] width = 4) (output wire [width-1:0] s,
    output wire cout, input wire [width-1:0] a, b, input wire cin);

    wire [width:0] c;
    assign c[0] = cin;
    assign cout = c[width];

    genvar n;
    generate
        for(n=0; n<width; n=n+1)
            fa fa(s[n], c[n+1], a[n], b[n], c[n]);
    endgenerate
endmodule


// module adder_16bit(output wire [15:0] sum, output wire cout, input wire [15:0] a, b,
//     input wire cin, clk, reset);
//     reg [7:0] ifa, ifb;
//     wire [7:0] ifanextw, ifbnextw;
//     reg if2;
//     wire if2nextw;
//     reg [7:0] if3;
//     wire [7:0] if3nextw;
//     wire [3:0] carry;
//
//     wide_adder w1(if3nextw[3:0], carry[0], a[3:0], b[3:0], cin);
//     wide_adder w2(if3nextw[7:4], if2nextw, a[7:4], b[7:4], carry[0]);
//     wide_adder w3(sum[11:8], carry[2], ifa[3:0], ifb[3:0], if2);
//     wide_adder w4(sum[15:12], carry[3], ifa[7:4], ifb[7:4], carry[2]);
//
//     always @(posedge clk, reset) begin
//         if (reset) begin
//             {ifa, ifb, if2, if3} <= {4'b0, 4'b0, 1'b0, 4'b0};
//         end
//         else begin
//             ifa <= ifanextw;
//             ifb <= ifbnextw;
//             if2 <= if2nextw;
//             if3 <= if3nextw;
//         end
//     end
//
//     assign sum[7:0] = if3;
//     assign {ifanextw, ifbnextw} = {a[15:8], b[15:8]};
//     assign cout = carry[3];
// endmodule

module adder_16bit(output wire [15:0] sum, output wire cout, input wire [15:0] a, b,
    input wire cin, clk, reset);
    reg [11:0] stage_1_a, stage_1_b;
    reg [7:0] stage_2_a, stage_2_b;
    reg [3:0] stage_3_a, stage_3_b;

    reg [3:0] sum_stage_0;
    reg [7:0] sum_stage_1;
    reg [11:0] sum_stage_2;

    wire [3:0] temp_0;
    wire [3:0] temp_1;
    wire [3:0] temp_2;
    wire [3:0] temp_3;

    wire carry_stage_0_out;
    reg carry_stage_1_in;
    wire carry_stage_1_out;
    reg carry_stage_2_in;
    wire carry_stage_2_out;
    reg carry_stage_3_in;
    wire carry_stage_3_out;

    wide_adder w1(temp_0, carry_stage_0_out, a[3:0], b[3:0], cin);
    wide_adder w2(temp_1, carry_stage_1_out, stage_1_a[3:0], stage_1_b[3:0], carry_stage_1_in);
    wide_adder w3(temp_2, carry_stage_2_out, stage_2_a[3:0], stage_2_b[3:0], carry_stage_2_in);
    wide_adder w4(sum[15:12], cout, stage_3_a[3:0], stage_3_b[3:0], carry_stage_3_in);

    always @(posedge clk, reset) begin
        if (reset) begin
            {carry_stage_1_in, carry_stage_2_in, carry_stage_3_in} <= {1'b0, 1'b0, 1'b0};
        end
        else begin
            sum_stage_0 = temp_0;
            sum_stage_1[3:0] <= sum_stage_0;
            sum_stage_1[7:4] = temp_1;
            sum_stage_2[7:0] <= sum_stage_1;
            sum_stage_2[11:8] = temp_2;

            stage_1_a <= a[15:4];
            stage_1_b <= b[15:4];

            stage_2_a <= stage_1_a[11:4];
            stage_2_b <= stage_1_b[11:4];

            stage_3_a <= stage_2_a[7:4];
            stage_3_b <= stage_2_b[7:4];

            carry_stage_1_in <= carry_stage_0_out;
            carry_stage_2_in <= carry_stage_1_out;
            carry_stage_3_in <= carry_stage_2_out;
        end
    end
    assign sum[11:0] = sum_stage_2;
endmodule




module tb_wide_adder_16bit();
    reg clk;
    reg [15:0] a, b;
    wire [15:0] sum;
    wire [15:0] sum_actual;
    reg c_in, rst;
    wire c_out;

    assign sum_actual = a+b;

    adder_16bit a1(
      .clk(clk),
      .sum(sum),
      .a(a),
      .b(b),
      .cin(c_in),
      .cout(c_out),
      .reset(rst)
      );

    initial begin
        $dumpfile("wide_adder.vcd");
        $dumpvars;
        rst = 1;
        a = 200;
        b = 0;
        clk = 0;
        c_in = 0;
        #50 rst = 0;
        #2000 $finish;
    end

    always
      #5 clk = ~clk;

    always@(posedge clk)
    begin
      a <= a+1;
      b <= b+1;
    end

endmodule

lab_7/wide_adder.vcd
$date
	Thu Apr 11 16:24:50 2019
$end
$version
	Icarus Verilog
$end
$timescale
	1s
$end
$scope module tb_wide_adder_16bit $end
$var wire 16 ! sum_actual [15:0] $end
$var wire 16 " sum [15:0] $end
$var wire 1 # c_out $end
$var reg 16 $ a [15:0] $end
$var reg 16 % b [15:0] $end
$var reg 1 & c_in $end
$var reg 1 ' clk $end
$var reg 1 ( rst $end
$scope module a1 $end
$var wire 16 ) a [15:0] $end
$var wire 16 * b [15:0] $end
$var wire 1 & cin $end
$var wire 1 ' clk $end
$var wire 1 ( reset $end
$var wire 4 + temp_2 [3:0] $end
$var wire 4 , temp_1 [3:0] $end
$var wire 4 - temp_0 [3:0] $end
$var wire 16 . sum [15:0] $end
$var wire 1 # cout $end
$var wire 1 / carry_stage_2_out $end
$var wire 1 0 carry_stage_1_out $end
$var wire 1 1 carry_stage_0_out $end
$var reg 1 2 carry_stage_1_in $end
$var reg 1 3 carry_stage_2_in $end
$var reg 1 4 carry_stage_3_in $end
$var reg 12 5 stage_1_a [11:0] $end
$var reg 12 6 stage_1_b [11:0] $end
$var reg 8 7 stage_2_a [7:0] $end
$var reg 8 8 stage_2_b [7:0] $end
$var reg 4 9 stage_3_a [3:0] $end
$var reg 4 : stage_3_b [3:0] $end
$var reg 4 ; sum_stage_0 [3:0] $end
$var reg 8 < sum_stage_1 [7:0] $end
$var reg 12 = sum_stage_2 [11:0] $end
$scope module w1 $end
$var wire 4 > a [3:0] $end
$var wire 4 ? b [3:0] $end
$var wire 1 & cin $end
$var wire 4 @ s [3:0] $end
$var wire 1 1 cout $end
$var wire 5 A c [4:0] $end
$scope begin genblk1[0] $end
$scope module fa $end
$var wire 1 B a $end
$var wire 1 C b $end
$var wire 1 D cin $end
$var wire 1 E s $end
$var wire 1 F cout $end
$upscope $end
$upscope $end
$scope begin genblk1[1] $end
$scope module fa $end
$var wire 1 G a $end
$var wire 1 H b $end
$var wire 1 I cin $end
$var wire 1 J s $end
$var wire 1 K cout $end
$upscope $end
$upscope $end
$scope begin genblk1[2] $end
$scope module fa $end
$var wire 1 L a $end
$var wire 1 M b $end
$var wire 1 N cin $end
$var wire 1 O s $end
$var wire 1 P cout $end
$upscope $end
$upscope $end
$scope begin genblk1[3] $end
$scope module fa $end
$var wire 1 Q a $end
$var wire 1 R b $end
$var wire 1 S cin $end
$var wire 1 T s $end
$var wire 1 U cout $end
$upscope $end
$upscope $end
$upscope $end
$scope module w2 $end
$var wire 4 V a [3:0] $end
$var wire 4 W b [3:0] $end
$var wire 1 2 cin $end
$var wire 4 X s [3:0] $end
$var wire 1 0 cout $end
$var wire 5 Y c [4:0] $end
$scope begin genblk1[0] $end
$scope module fa $end
$var wire 1 Z a $end
$var wire 1 [ b $end
$var wire 1 \ cin $end
$var wire 1 ] s $end
$var wire 1 ^ cout $end
$upscope $end
$upscope $end
$scope begin genblk1[1] $end
$scope module fa $end
$var wire 1 _ a $end
$var wire 1 ` b $end
$var wire 1 a cin $end
$var wire 1 b s $end
$var wire 1 c cout $end
$upscope $end
$upscope $end
$scope begin genblk1[2] $end
$scope module fa $end
$var wire 1 d a $end
$var wire 1 e b $end
$var wire 1 f cin $end
$var wire 1 g s $end
$var wire 1 h cout $end
$upscope $end
$upscope $end
$scope begin genblk1[3] $end
$scope module fa $end
$var wire 1 i a $end
$var wire 1 j b $end
$var wire 1 k cin $end
$var wire 1 l s $end
$var wire 1 m cout $end
$upscope $end
$upscope $end
$upscope $end
$scope module w3 $end
$var wire 4 n a [3:0] $end
$var wire 4 o b [3:0] $end
$var wire 1 3 cin $end
$var wire 4 p s [3:0] $end
$var wire 1 / cout $end
$var wire 5 q c [4:0] $end
$scope begin genblk1[0] $end
$scope module fa $end
$var wire 1 r a $end
$var wire 1 s b $end
$var wire 1 t cin $end
$var wire 1 u s $end
$var wire 1 v cout $end
$upscope $end
$upscope $end
$scope begin genblk1[1] $end
$scope module fa $end
$var wire 1 w a $end
$var wire 1 x b $end
$var wire 1 y cin $end
$var wire 1 z s $end
$var wire 1 { cout $end
$upscope $end
$upscope $end
$scope begin genblk1[2] $end
$scope module fa $end
$var wire 1 | a $end
$var wire 1 } b $end
$var wire 1 ~ cin $end
$var wire 1 !" s $end
$var wire 1 "" cout $end
$upscope $end
$upscope $end
$scope begin genblk1[3] $end
$scope module fa $end
$var wire 1 #" a $end
$var wire 1 $" b $end
$var wire 1 %" cin $end
$var wire 1 &" s $end
$var wire 1 '" cout $end
$upscope $end
$upscope $end
$upscope $end
$scope module w4 $end
$var wire 4 (" a [3:0] $end
$var wire 4 )" b [3:0] $end
$var wire 1 4 cin $end
$var wire 4 *" s [3:0] $end
$var wire 1 # cout $end
$var wire 5 +" c [4:0] $end
$scope begin genblk1[0] $end
$scope module fa $end
$var wire 1 ," a $end
$var wire 1 -" b $end
$var wire 1 ." cin $end
$var wire 1 /" s $end
$var wire 1 0" cout $end
$upscope $end
$upscope $end
$scope begin genblk1[1] $end
$scope module fa $end
$var wire 1 1" a $end
$var wire 1 2" b $end
$var wire 1 3" cin $end
$var wire 1 4" s $end
$var wire 1 5" cout $end
$upscope $end
$upscope $end
$scope begin genblk1[2] $end
$scope module fa $end
$var wire 1 6" a $end
$var wire 1 7" b $end
$var wire 1 8" cin $end
$var wire 1 9" s $end
$var wire 1 :" cout $end
$upscope $end
$upscope $end
$scope begin genblk1[3] $end
$scope module fa $end
$var wire 1 ;" a $end
$var wire 1 <" b $end
$var wire 1 =" cin $end
$var wire 1 >" s $end
$var wire 1 ?" cout $end
$upscope $end
$upscope $end
$upscope $end
$upscope $end
$upscope $end
$enddefinitions $end
#0
$dumpvars
x?"
x>"
x="
x<"
x;"
x:"
x9"
x8"
x7"
x6"
x5"
x4"
x3"
x2"
x1"
x0"
x/"
0."
x-"
x,"
bx0 +"
bx *"
bx )"
bx ("
x'"
x&"
x%"
x$"
x#"
x""
x!"
x~
x}
x|
x{
xz
xy
xx
xw
xv
xu
0t
xs
xr
bx0 q
bx p
bx o
bx n
xm
xl
xk
xj
xi
xh
xg
xf
xe
xd
xc
xb
xa
x`
x_
x^
x]
0\
x[
xZ
bx0 Y
bx X
bx W
bx V
0U
1T
0S
0R
1Q
0P
0O
0N
0M
0L
0K
0J
0I
0H
0G
0F
0E
0D
0C
0B
b0 A
b1000 @
b0 ?
b1000 >
bx =
bx <
bx ;
bx :
bx 9
bx 8
bx 7
bx 6
bx 5
04
03
02
01
x0
x/
bx .
b1000 -
bx ,
bx +
b0 *
b11001000 )
1(
0'
0&
b0 %
b11001000 $
x#
bx "
b11001000 !
$end
#5
b1010 -
b1010 @
1J
1I
b10 A
1F
1C
1B
b1 ?
b1001 >
b1 %
b1 *
b11001010 !
b11001001 $
b11001001 )
1'
#10
0'
#15
0J
b1100 -
b1100 @
1O
0I
1N
0F
b100 A
1K
0C
1H
0B
1G
b10 ?
b1010 >
b10 %
b10 *
b11001100 !
b11001010 $
b11001010 )
1'
#20
0'
#25
b1110 -
b1110 @
1J
1I
b110 A
1F
1C
1B
b11 ?
b1011 >
b11 %
b11 *
b11001110 !
b11001011 $
b11001011 )
1'
#30
0'
#35
11
0O
0J
b0 -
b0 @
0T
1U
0N
0I
1S
0K
0F
b11000 A
1P
0C
0H
1M
0B
0G
1L
b100 ?
b1100 >
b100 %
b100 *
b11010000 !
b11001100 $
b11001100 )
1'
#40
0'
#45
b10 -
b10 @
1J
1I
b11010 A
1F
1C
1B
b101 ?
b1101 >
b101 %
b101 *
b11010010 !
b11001101 $
b11001101 )
1'
#50
00
1l
0m
0k
1g
0h
0f
0b
0c
0a
b1101 ,
b1101 X
1]
0^
0[
0`
0e
0j
0Z
0_
1d
1i
x."
xt
1\
b0 W
b1100 V
bx +"
x4
bx q
x3
b1 Y
12
b0 6
b1100 5
bx0010 <
b10 ;
0'
0(
#55
0/
0&"
0'"
0%"
0!"
0""
0~
0z
0{
0J
b100 -
b100 @
1O
0y
0I
1N
b0 +
b0 p
0u
0v
0F
b11100 A
1K
0s
0x
0}
0$"
0r
0w
0|
0#"
0C
1H
0B
1G
0t
b0 o
b0 n
b110 ?
b1110 >
b0 q
03
b0 8
b0 7
bx11010010 "
bx11010010 .
bx11010010 =
b110 %
b110 *
b11010100 !
b11001110 $
b11001110 )
b11010010 <
1'
#60
0'
#65
0#
0>"
0?"
0="
09"
0:"
08"
b110 -
b110 @
1J
04"
05"
1I
03"
b11110 A
1F
b0 *"
0/"
00"
1C
1B
0."
0-"
02"
07"
0<"
0,"
01"
06"
0;"
b111 ?
b1111 >
b0 +"
04
b0 :
b0 )"
b0 9
b0 ("
b11010100 <
b111 %
b111 *
b11010110 !
b11001111 $
b11001111 )
b11010010 "
b11010010 .
b11010010 =
b100 ;
1'
#70
0'
#75
01
0O
1T
0U
b1000 -
b1000 @
0J
0N
0S
0I
0K
0P
b0 A
0F
0C
0H
0M
1R
0B
0G
0L
0Q
b1000 ?
b0 >
b11010100 "
b11010100 .
b11010100 =
b11010110 <
b1000 %
b1000 *
b11011000 !
b11010000 $
b11010000 )
b110 ;
1'
#80
0'
#85
b1010 -
b1010 @
1J
1I
b10 A
1F
1Z
1C
1B
0\
b1101 V
b1001 ?
b1 >
b0 Y
02
b1101 5
b11010110 "
b11010110 .
b11010110 =
b11011000 <
b1001 %
b1001 *
b11011010 !
b11010001 $
b11010001 )
b1000 ;
1'
#90
0'
#95
0J
b1100 -
b1100 @
1O
0I
1N
0F
b100 A
1K
0C
1H
0B
1G
b1010 ?
b10 >
b11011000 "
b11011000 .
b11011000 =
b11011010 <
b1010 %
b1010 *
b11011100 !
b11010010 $
b11010010 )
b1010 ;
1'
#100
0'
#105
b1110 -
b1110 @
1J
1I
b110 A
1F
1C
1B
b1011 ?
b11 >
b11011010 "
b11011010 .
b11011010 =
b11011100 <
b1011 %
b1011 *
b11011110 !
b11010011 $
b11010011 )
b1100 ;
1'
#110
0'
#115
11
0O
0J
b0 -
b0 @
0T
1U
0N
0I
1S
0K
0F
b11000 A
1P
0C
0H
1M
0B
0G
1L
b1100 ?
b100 >
b11011100 "
b11011100 .
b11011100 =
b11011110 <
b1100 %
b1100 *
b11100000 !
b11010100 $
b11010100 )
b1110 ;
1'
#120
0'
#125
b10 -
b10 @
1J
1b
1I
1a
b11010 A
1F
b1110 ,
b1110 X
0]
1^
1C
1B
1\
b1101 ?
b101 >
b11 Y
12
b11011110 "
b11011110 .
b11011110 =
b11010000 <
b1101 %
b1101 *
b11100010 !
b11010101 $
b11010101 )
b0 ;
1'
#130
0'
#135
0J
b100 -
b100 @
1O
0I
1N
0F
b11100 A
1K
0C
1H
0B
1G
b1110 ?
b110 >
b11100000 "
b11100000 .
b11100000 =
b1110 %
b1110 *
b11100100 !
b11010110 $
b11010110 )
b11100010 <
b10 ;
1'
#140
0'
#145
b110 -
b110 @
1J
1I
b11110 A
1F
1C
1B
b1111 ?
b111 >
b11100010 "
b11100010 .
b11100010 =
b11100100 <
b1111 %
b1111 *
b11100110 !
b11010111 $
b11010111 )
b100 ;
1'
#150
0'
#155
01
0O
1T
0U
b1000 -
b1000 @
0J
0N
0S
0I
0K
0P
b0 A
0F
0C
0H
0M
0R
0B
0G
0L
1Q
b0 ?
b1000 >
b11100100 "
b11100100 .
b11100100 =
b11100110 <
b10000 %
b10000 *
b11101000 !
b11011000 $
b11011000 )
b110 ;
1'
#160
0'
#165
b1010 -
b1010 @
1J
1I
b10 A
1F
1[
1C
1B
0\
b1 W
b1 ?
b1001 >
b10 Y
02
b1 6
b11100110 "
b11100110 .
b11100110 =
b11101000 <
b10001 %
b10001 *
b11101010 !
b11011001 $
b11011001 )
b1000 ;
1'
#170
0'
#175
0J
b1100 -
b1100 @
1O
0I
1N
0F
b100 A
1K
0C
1H
0B
1G
b10 ?
b1010 >
b11101000 "
b11101000 .
b11101000 =
b11101010 <
b10010 %
b10010 *
b11101100 !
b11011010 $
b11011010 )
b1010 ;
1'
#180
0'
#185
b1110 -
b1110 @
1J
1I
b110 A
1F
1C
1B
b11 ?
b1011 >
b11101010 "
b11101010 .
b11101010 =
b11101100 <
b10011 %
b10011 *
b11101110 !
b11011011 $
b11011011 )
b1100 ;
1'
#190
0'
#195
11
0O
0J
b0 -
b0 @
0T
1U
0N
0I
1S
0K
0F
b11000 A
1P
0C
0H
1M
0B
0G
1L
b100 ?
b1100 >
b11101100 "
b11101100 .
b11101100 =
b11101110 <
b10100 %
b10100 *
b11110000 !
b11011100 $
b11011100 )
b1110 ;
1'
#200
0'
#205
b10 -
b10 @
1J
1I
b11010 A
1F
b1111 ,
b1111 X
1]
1C
1B
1\
b101 ?
b1101 >
b11 Y
12
b11101110 "
b11101110 .
b11101110 =
b11100000 <
b10101 %
b10101 *
b11110010 !
b11011101 $
b11011101 )
b0 ;
1'
#210
0'
#215
0J
b100 -
b100 @
1O
0I
1N
0F
b11100 A
1K
0C
1H
0B
1G
b110 ?
b1110 >
b11110000 "
b11110000 .
b11110000 =
b10110 %
b10110 *
b11110100 !
b11011110 $
b11011110 )
b11110010 <
b10 ;
1'
#220
0'
#225
b110 -
b110 @
1J
1I
b11110 A
1F
1C
1B
b111 ?
b1111 >
b11110010 "
b11110010 .
b11110010 =
b11110100 <
b10111 %
b10111 *
b11110110 !
b11011111 $
b11011111 )
b100 ;
1'
#230
0'
#235
01
0O
1T
0U
b1000 -
b1000 @
0J
0N
0S
0I
0K
0P
b0 A
0F
0C
0H
0M
1R
0B
0G
0L
0Q
b1000 ?
b0 >
b11110100 "
b11110100 .
b11110100 =
b11110110 <
b11000 %
b11000 *
b11111000 !
b11100000 $
b11100000 )
b110 ;
1'
#240
0'
#245
00
1l
0m
0k
1g
0h
b1010 -
b1010 @
1J
0a
0f
1I
0^
b1111 ,
b1111 X
1b
0c
b10 A
1F
0Z
1_
1C
1B
0\
b1110 V
b1001 ?
b1 >
b0 Y
02
b1110 5
b11110110 "
b11110110 .
b11110110 =
b11111000 <
b11001 %
b11001 *
b11111010 !
b11100001 $
b11100001 )
b1000 ;
1'
#250
0'
#255
0J
b1100 -
b1100 @
1O
0I
1N
0F
b100 A
1K
0C
1H
0B
1G
b1010 ?
b10 >
b11111000 "
b11111000 .
b11111000 =
b11111010 <
b11010 %
b11010 *
b11111100 !
b11100010 $
b11100010 )
b1010 ;
1'
#260
0'
#265
b1110 -
b1110 @
1J
1I
b110 A
1F
1C
1B
b1011 ?
b11 >
b11111010 "
b11111010 .
b11111010 =
b11111100 <
b11011 %
b11011 *
b11111110 !
b11100011 $
b11100011 )
b1100 ;
1'
#270
0'
#275
11
0O
0J
b0 -
b0 @
0T
1U
0N
0I
1S
0K
0F
b11000 A
1P
0C
0H
1M
0B
0G
1L
b1100 ?
b100 >
b11111100 "
b11111100 .
b11111100 =
b11111110 <
b11100 %
b11100 *
b100000000 !
b11100100 $
b11100100 )
b1110 ;
1'
#280
0'
#285
10
0l
1m
1k
0g
1h
1f
b10 -
b10 @
1J
0b
1c
1I
1a
b11010 A
1F
b0 ,
b0 X
0]
1^
1C
1B
1\
b1101 ?
b101 >
b11111 Y
12
b11111110 "
b11111110 .
b11111110 =
b11110000 <
b11101 %
b11101 *
b100000010 !
b11100101 $
b11100101 )
b0 ;
1'
#290
0'
#295
0J
b100 -
b100 @
1O
0I
1N
0F
b11100 A
1K
b1 +
b1 p
1u
0C
1H
0B
1G
1t
b1110 ?
b110 >
b1 q
13
b0 "
b0 .
b0 =
b11110 %
b11110 *
b100000100 !
b11100110 $
b11100110 )
b10 <
b10 ;
1'
#300
0'
#305
b110 -
b110 @
1J
1I
b11110 A
1F
1C
1B
b1111 ?
b111 >
b100 <
b11111 %
b11111 *
b100000110 !
b11100111 $
b11100111 )
b100000010 "
b100000010 .
b100000010 =
b100 ;
1'
#310
0'
#315
01
0O
1T
0U
b1000 -
b1000 @
0J
0N
0S
0I
0K
0P
b0 A
0F
0C
0H
0M
0R
0B
0G
0L
1Q
b0 ?
b1000 >
b100000100 "
b100000100 .
b100000100 =
b110 <
b100000 %
b100000 *
b100001000 !
b11101000 $
b11101000 )
b110 ;
1'
#320
0'
#325
b1010 -
b1010 @
1J
1I
0a
b0 ,
b0 X
0b
b10 A
1F
0^
0[
1`
1C
1B
0\
b10 W
b1 ?
b1001 >
b11100 Y
02
b10 6
b100000110 "
b100000110 .
b100000110 =
b1000 <
b100001 %
b100001 *
b100001010 !
b11101001 $
b11101001 )
b1000 ;
1'
#330
0'
#335
0J
b1100 -
b1100 @
1O
0I
1N
0F
b100 A
1K
0C
1H
0B
1G
b10 ?
b1010 >
b100001000 "
b100001000 .
b100001000 =
b1010 <
b100010 %
b100010 *
b100001100 !
b11101010 $
b11101010 )
b1010 ;
1'
#340
0'
#345
b1110 -
b1110 @
1J
1I
b110 A
1F
1C
1B
b11 ?
b1011 >
b100001010 "
b100001010 .
b100001010 =
b1100 <
b100011 %
b100011 *
b100001110 !
b11101011 $
b11101011 )
b1100 ;
1'
#350
0'
#355
11
0O
0J
b0 -
b0 @
0T
1U
0N
0I
1S
0K
0F
b11000 A
1P
0C
0H
1M
0B
0G
1L
b100 ?
b1100 >
b100001100 "
b100001100 .
b100001100 =
b1110 <
b100100 %
b100100 *
b100010000 !
b11101100 $
b11101100 )
b1110 ;
1'
#360
0'
#365
b10 -
b10 @
1J
1I
b11010 A
1F
b1 ,
b1 X
1]
1C
1B
1\
b101 ?
b1101 >
b11101 Y
12
b100001110 "
b100001110 .
b100001110 =
b0 <
b100101 %
b100101 *
b100010010 !
b11101101 $
b11101101 )
b0 ;
1'
#370
0'
#375
0J
b100 -
b100 @
1O
0I
1N
0F
b11100 A
1K
0C
1H
0B
1G
b110 ?
b1110 >
b100010000 "
b100010000 .
b100010000 =
b100110 %
b100110 *
b100010100 !
b11101110 $
b11101110 )
b10010 <
b10 ;
1'
#380
0'
#385
b110 -
b110 @
1J
1I
b11110 A
1F
1C
1B
b111 ?
b1111 >
b100010010 "
b100010010 .
b100010010 =
b10100 <
b100111 %
b100111 *
b100010110 !
b11101111 $
b11101111 )
b100 ;
1'
#390
0'
#395
01
0O
1T
0U
b1000 -
b1000 @
0J
0N
0S
0I
0K
0P
b0 A
0F
0C
0H
0M
1R
0B
0G
0L
0Q
b1000 ?
b0 >
b100010100 "
b100010100 .
b100010100 =
b10110 <
b101000 %
b101000 *
b100011000 !
b11110000 $
b11110000 )
b110 ;
1'
#400
0'
#405
b1010 -
b1010 @
1J
1I
b10 A
1F
1Z
1C
1B
0\
b1111 V
b1001 ?
b1 >
b11100 Y
02
b1111 5
b100010110 "
b100010110 .
b100010110 =
b11000 <
b101001 %
b101001 *
b100011010 !
b11110001 $
b11110001 )
b1000 ;
1'
#410
0'
#415
0J
b1100 -
b1100 @
1O
0I
1N
0F
b100 A
1K
0C
1H
0B
1G
b1010 ?
b10 >
b100011000 "
b100011000 .
b100011000 =
b11010 <
b101010 %
b101010 *
b100011100 !
b11110010 $
b11110010 )
b1010 ;
1'
#420
0'
#425
b1110 -
b1110 @
1J
1I
b110 A
1F
1C
1B
b1011 ?
b11 >
b100011010 "
b100011010 .
b100011010 =
b11100 <
b101011 %
b101011 *
b100011110 !
b11110011 $
b11110011 )
b1100 ;
1'
#430
0'
#435
11
0O
0J
b0 -
b0 @
0T
1U
0N
0I
1S
0K
0F
b11000 A
1P
0C
0H
1M
0B
0G
1L
b1100 ?
b100 >
b100011100 "
b100011100 .
b100011100 =
b11110 <
b101100 %
b101100 *
b100100000 !
b11110100 $
b11110100 )
b1110 ;
1'
#440
0'
#445
b10 -
b10 @
1J
1b
1I
1a
b11010 A
1F
b10 ,
b10 X
0]
1^
1C
1B
1\
b1101 ?
b101 >
b11111 Y
12
b100011110 "
b100011110 .
b100011110 =
b10000 <
b101101 %
b101101 *
b100100010 !
b11110101 $
b11110101 )
b0 ;
1'
#450
0'
#455
0J
b100 -
b100 @
1O
0I
1N
0F
b11100 A
1K
0C
1H
0B
1G
b1110 ?
b110 >
b100100000 "
b100100000 .
b100100000 =
b101110 %
b101110 *
b100100100 !
b11110110 $
b11110110 )
b100010 <
b10 ;
1'
#460
0'
#465
b110 -
b110 @
1J
1I
b11110 A
1F
1C
1B
b1111 ?
b111 >
b100100010 "
b100100010 .
b100100010 =
b100100 <
b101111 %
b101111 *
b100100110 !
b11110111 $
b11110111 )
b100 ;
1'
#470
0'
#475
01
0O
1T
0U
b1000 -
b1000 @
0J
0N
0S
0I
0K
0P
b0 A
0F
0C
0H
0M
0R
0B
0G
0L
1Q
b0 ?
b1000 >
b100100100 "
b100100100 .
b100100100 =
b100110 <
b110000 %
b110000 *
b100101000 !
b11111000 $
b11111000 )
b110 ;
1'
#480
0'
#485
b1010 -
b1010 @
1J
1I
b10 A
1F
1[
1C
1B
0\
b11 W
b1 ?
b1001 >
b11110 Y
02
b11 6
b100100110 "
b100100110 .
b100100110 =
b101000 <
b110001 %
b110001 *
b100101010 !
b11111001 $
b11111001 )
b1000 ;
1'
#490
0'
#495
0J
b1100 -
b1100 @
1O
0I
1N
0F
b100 A
1K
0C
1H
0B
1G
b10 ?
b1010 >
b100101000 "
b100101000 .
b100101000 =
b101010 <
b110010 %
b110010 *
b100101100 !
b11111010 $
b11111010 )
b1010 ;
1'
#500
0'
#505
b1110 -
b1110 @
1J
1I
b110 A
1F
1C
1B
b11 ?
b1011 >
b100101010 "
b100101010 .
b100101010 =
b101100 <
b110011 %
b110011 *
b100101110 !
b11111011 $
b11111011 )
b1100 ;
1'
#510
0'
#515
11
0O
0J
b0 -
b0 @
0T
1U
0N
0I
1S
0K
0F
b11000 A
1P
0C
0H
1M
0B
0G
1L
b100 ?
b1100 >
b100101100 "
b100101100 .
b100101100 =
b101110 <
b110100 %
b110100 *
b100110000 !
b11111100 $
b11111100 )
b1110 ;
1'
#520
0'
#525
b10 -
b10 @
1J
1I
b11010 A
1F
b11 ,
b11 X
1]
1C
1B
1\
b101 ?
b1101 >
b11111 Y
12
b100101110 "
b100101110 .
b100101110 =
b100000 <
b110101 %
b110101 *
b100110010 !
b11111101 $
b11111101 )
b0 ;
1'
#530
0'
#535
0J
b100 -
b100 @
1O
0I
1N
0F
b11100 A
1K
0C
1H
0B
1G
b110 ?
b1110 >
b100110000 "
b100110000 .
b100110000 =
b110110 %
b110110 *
b100110100 !
b11111110 $
b11111110 )
b110010 <
b10 ;
1'
#540
0'
#545
b110 -
b110 @
1J
1I
b11110 A
1F
1C
1B
b111 ?
b1111 >
b100110010 "
b100110010 .
b100110010 =
b110100 <
b110111 %
b110111 *
b100110110 !
b11111111 $
b11111111 )
b100 ;
1'
#550
0'
#555
01
0O
1T
0U
b1000 -
b1000 @
0J
0N
0S
0I
0K
0P
b0 A
0F
0C
0H
0M
1R
0B
0G
0L
0Q
b1000 ?
b0 >
b100110100 "
b100110100 .
b100110100 =
b110110 <
b111000 %
b111000 *
b100111000 !
b100000000 $
b100000000 )
b110 ;
1'
#560
0'
#565
0f
0c
b1010 -
b1010 @
1J
0a
0k
00
1I
0^
1b
0g
0h
b11 ,
b11 X
0l
0m
b10 A
1F
0Z
0_
0d
0i
1C
1B
0\
b0 V
b1001 ?
b1 >
b0 Y
02
b10000 5
b100110110 "
b100110110 .
b100110110 =
b111000 <
b111001 %
b111001 *
b100111010 !
b100000001 $
b100000001 )
b1000 ;
1'
#570
0'
#575
0J
b1100 -
b1100 @
1O
0I
1N
0F
b100 A
1K
1r
0C
1H
0B
1G
0t
b1 n
b1010 ?
b10 >
b0 q
03
b1 7
b100111000 "
b100111000 .
b100111000 =
b111010 <
b111010 %
b111010 *
b100111100 !
b100000010 $
b100000010 )
b1010 ;
1'
#580
0'
#585
b1110 -
b1110 @
1J
1I
b110 A
1F
1C
1B
b1011 ?
b11 >
b100111010 "
b100111010 .
b100111010 =
b111100 <
b111011 %
b111011 *
b100111110 !
b100000011 $
b100000011 )
b1100 ;
1'
#590
0'
#595
11
0O
0J
b0 -
b0 @
0T
1U
0N
0I
1S
0K
0F
b11000 A
1P
0C
0H
1M
0B
0G
1L
b1100 ?
b100 >
b100111100 "
b100111100 .
b100111100 =
b111110 <
b111100 %
b111100 *
b101000000 !
b100000100 $
b100000100 )
b1110 ;
1'
#600
0'
#605
1g
1f
b10 -
b10 @
1J
0b
1c
1I
1a
b11010 A
1F
b100 ,
b100 X
0]
1^
1C
1B
1\
b1101 ?
b101 >
b111 Y
12
b100111110 "
b100111110 .
b100111110 =
b110000 <
b111101 %
b111101 *
b101000010 !
b100000101 $
b100000101 )
b0 ;
1'
#610
0'
#615
0J
b100 -
b100 @
1O
0I
1N
0F
b11100 A
1K
0C
1H
0B
1G
b1110 ?
b110 >
b101000000 "
b101000000 .
b101000000 =
b111110 %
b111110 *
b101000100 !
b100000110 $
b100000110 )
b1000010 <
b10 ;
1'
#620
0'
#625
b110 -
b110 @
1J
1I
b11110 A
1F
1C
1B
b1111 ?
b111 >
b101000010 "
b101000010 .
b101000010 =
b1000100 <
b111111 %
b111111 *
b101000110 !
b100000111 $
b100000111 )
b100 ;
1'
#630
0'
#635
01
0O
1T
0U
b1000 -
b1000 @
0J
0N
0S
0I
0K
0P
b0 A
0F
0C
0H
0M
0R
0B
0G
0L
1Q
b0 ?
b1000 >
b101000100 "
b101000100 .
b101000100 =
b1000110 <
b1000000 %
b1000000 *
b101001000 !
b100001000 $
b100001000 )
b110 ;
1'
#640
0'
